lilyanncabinets/__init__.py
lilyanncabinets/main.py
lilyanncabinets/scan.py
lilyanncabinets/sheets.py
lilyanncabinets-2.0.2.dist-info/LICENSE
lilyanncabinets-2.0.2.dist-info/METADATA
lilyanncabinets-2.0.2.dist-info/WHEEL
lilyanncabinets-2.0.2.dist-info/top_level.txt
lilyanncabinets-2.0.2.dist-info/RECORD
