Metadata-Version: 2.1
Name: lilyanncabinets
Version: 2.0.2
Summary: Package for use by Lily Ann Cabinets
Home-page: https://github.com/JosephCaligiuri/lilyanncabinets
Author: Joseph Caligiuri
Author-email: josephcaligiuri1@gmail.com
Classifier: Programming Language :: Python :: 3
Classifier: License :: OSI Approved :: MIT License
Classifier: Operating System :: OS Independent
Requires-Python: >=3.6
License-File: LICENSE
